LICENSE
LONG_DESCRIPTION.rst
MANIFEST.in
README.md
VERSION
setup.py
payabbhi/__init__.py
payabbhi/client.py
payabbhi/error.py
payabbhi/http_client.py
payabbhi.egg-info/PKG-INFO
payabbhi.egg-info/SOURCES.txt
payabbhi.egg-info/dependency_links.txt
payabbhi.egg-info/requires.txt
payabbhi.egg-info/top_level.txt
payabbhi/resources/__init__.py
payabbhi/resources/api_resource.py
payabbhi/resources/beneficiary_account.py
payabbhi/resources/customer.py
payabbhi/resources/empty_class.py
payabbhi/resources/event.py
payabbhi/resources/invoice.py
payabbhi/resources/invoice_item.py
payabbhi/resources/list.py
payabbhi/resources/order.py
payabbhi/resources/payment.py
payabbhi/resources/payment_link.py
payabbhi/resources/plan.py
payabbhi/resources/product.py
payabbhi/resources/refund.py
payabbhi/resources/settlement.py
payabbhi/resources/subscription.py
payabbhi/resources/transfer.py
payabbhi/resources/virtual_account.py
payabbhi/test/__init__.py
payabbhi/test/helpers.py
payabbhi/test/test_api_resource.py
payabbhi/test/test_beneficiary_account.py
payabbhi/test/test_client_utility.py
payabbhi/test/test_customer.py
payabbhi/test/test_event.py
payabbhi/test/test_http_client.py
payabbhi/test/test_invoice.py
payabbhi/test/test_invoice_item.py
payabbhi/test/test_order.py
payabbhi/test/test_payment.py
payabbhi/test/test_payment_link.py
payabbhi/test/test_plan.py
payabbhi/test/test_product.py
payabbhi/test/test_refund.py
payabbhi/test/test_settlement.py
payabbhi/test/test_subscription.py
payabbhi/test/test_transfer.py
payabbhi/test/test_virtual_account.py
payabbhi/utility/__init__.py
payabbhi/utility/utility.py