Metadata-Version: 1.1
Name: payabbhi
Version: 1.0.4
Summary: Payabbhi Python package provides client library for Payabbhi API's
Home-page: https://github.com/payabbhi/payabbhi-python
Author: Team Payabbhi
Author-email: support@payabbhi.com
License: MIT
Keywords: payabbhi payment processing api checkout india
Platform: UNKNOWN
Classifier: Development Status :: 5 - Production/Stable
Classifier: Intended Audience :: Developers
Classifier: Operating System :: OS Independent
Classifier: License :: OSI Approved :: MIT License
Classifier: Programming Language :: Python
Classifier: Programming Language :: Python :: 2.6
Classifier: Programming Language :: Python :: 2.7
Classifier: Programming Language :: Python :: 3.3
Classifier: Programming Language :: Python :: 3.4
Classifier: Programming Language :: Python :: 3.5
Classifier: Programming Language :: Python :: 3.6
